match_predicting_pub_api/__init__.py
match_predicting_pub_api/api_client.py
match_predicting_pub_api/api_response.py
match_predicting_pub_api/configuration.py
match_predicting_pub_api/exceptions.py
match_predicting_pub_api/py.typed
match_predicting_pub_api/rest.py
match_predicting_pub_api/api/__init__.py
match_predicting_pub_api/api/dummy_api.py
match_predicting_pub_api/api/import_api.py
match_predicting_pub_api/api/testing_api.py
match_predicting_pub_api/api/training_api.py
match_predicting_pub_api/models/__init__.py
match_predicting_pub_api/models/dummy_dto.py
match_predicting_pub_api/models/fcm_topic.py
match_predicting_pub_api/models/finished_import_status.py
match_predicting_pub_api/models/import_dto.py
match_predicting_pub_api/models/import_finished_message.py
match_predicting_pub_api/models/import_progress_dto.py
match_predicting_pub_api/models/import_type.py
match_predicting_pub_api/models/progress_dto.py
match_predicting_pub_api/models/testing_dto.py
match_predicting_pub_api/models/training_dto.py
match_predicting_pub_api/models/training_network_dto.py
match_predicting_pub_api/models/training_progress_dto.py
match_predicting_pub_api/models/training_request_dto.py
match_predicting_pub_api/models/training_result_dto.py
match_predicting_pub_api/models/user_role_enum.py
match_predicting_pub_api-6.12.dist-info/METADATA
match_predicting_pub_api-6.12.dist-info/WHEEL
match_predicting_pub_api-6.12.dist-info/top_level.txt
match_predicting_pub_api-6.12.dist-info/RECORD
