Metadata-Version: 2.4
Name: match-predicting-pub-api
Version: 6.12
Summary: Match Predicting Application Public API
Home-page: https://github.com/magistvan/match-predicting-ann-server-client
Author: István Mag
Author-email: magistvan@yahoo.com
Keywords: OpenAPI,OpenAPI-Generator,Match Predicting Application Public API
Requires-Dist: urllib3<3.0.0,>=1.25.3
Requires-Dist: python-dateutil
Requires-Dist: pydantic<2,>=1.10.5
Requires-Dist: aenum
Dynamic: author
Dynamic: author-email
Dynamic: description
Dynamic: description-content-type
Dynamic: home-page
Dynamic: keywords
Dynamic: requires-dist
Dynamic: summary
